elevate/__init__.py
elevate/apps.py
elevate/decorators.py
elevate/forms.py
elevate/middleware.py
elevate/mixins.py
elevate/settings.py
elevate/signals.py
elevate/utils.py
elevate/views.py
django_elevate-2.0.3.dist-info/LICENSE
django_elevate-2.0.3.dist-info/METADATA
django_elevate-2.0.3.dist-info/WHEEL
django_elevate-2.0.3.dist-info/top_level.txt
django_elevate-2.0.3.dist-info/zip-safe
django_elevate-2.0.3.dist-info/RECORD
